CovReg/__init__.py
CovReg/cole.py
CovReg/covreg.py
CovReg/graphcovreg.py
DyGraph/RootDygl.py
DyGraph/__init__.py
DyGraph/dyg_outer_em.py
DyGraph/dygl_inner_em.py
DyGraph/dygl_laplace.py
DyGraph/dygl_utils.py
DyGraph/sgl_inner_em.py
DyGraph/sgl_kcomp.py
DyGraph/sgl_laplace.py
DyGraph/sgl_outer_em.py
DyGraph-0.0.12.dist-info/LICENSE
DyGraph-0.0.12.dist-info/METADATA
DyGraph-0.0.12.dist-info/WHEEL
DyGraph-0.0.12.dist-info/top_level.txt
DyGraph-0.0.12.dist-info/RECORD
