Metadata-Version: 2.1
Name: DyGraph
Version: 0.0.12
Summary: A package for estimating dynamic graphical lasso with heavy tailed distributions
Home-page: https://github.com/ragnarlevi/DyGraph
Author: ragnarlevi
License: MIT
Project-URL: Bug Tracker, https://github.com/ragnarlevi/DyGraph/issues
Platform: unix
Platform: linux
Platform: osx
Platform: cygwin
Platform: win32
Classifier: Programming Language :: Python :: 3
Classifier: Programming Language :: Python :: 3 :: Only
Classifier: Programming Language :: Python :: 3.7
Classifier: Programming Language :: Python :: 3.8
Classifier: Programming Language :: Python :: 3.9
Classifier: Programming Language :: Python :: 3.10
Classifier: License :: OSI Approved :: MIT License
Classifier: Operating System :: OS Independent
Requires-Python: >=3.7
License-File: LICENSE
Requires-Dist: scipy >=1.6.1
Requires-Dist: numpy >=1.20.1
Requires-Dist: tqdm >=4.65.0
Provides-Extra: testing
Requires-Dist: pytest >=7.3.0 ; extra == 'testing'
Requires-Dist: pytest-cov >=2.0 ; extra == 'testing'
Requires-Dist: tox >=3.24 ; extra == 'testing'
